jurigged/__init__.py
jurigged/__main__.py
jurigged/codetools.py
jurigged/live.py
jurigged/parse.py
jurigged/recode.py
jurigged/register.py
jurigged/rescript.py
jurigged/runpy.py
jurigged/utils.py
jurigged/version.py
jurigged/loop/__init__.py
jurigged/loop/basic.py
jurigged/loop/develoop.py
jurigged/loop/richloop.py
jurigged-0.6.1.dist-info/METADATA
jurigged-0.6.1.dist-info/WHEEL
jurigged-0.6.1.dist-info/entry_points.txt
jurigged-0.6.1.dist-info/licenses/LICENSE
jurigged-0.6.1.dist-info/RECORD
